{"dependencies":[{"name":"react","loc":{"line":1,"column":18}}],"generated":{"js":"\"use strict\";\n\nObject.defineProperty(exports, \"__esModule\", {\n  value: true\n});\n\nvar _react = require(\"react\");\n\nvar _react2 = _interopRequireDefault(_react);\n\nfunction _interopRequireDefault(obj) { return obj && obj.__esModule ? obj : { default: obj }; }\n\nclass App extends _react2.default.Component {\n  constructor(props) {\n    super(props);\n\n    this.state = {\n      count: 0\n    };\n    this.onClick = this.onClick.bind(this);\n  }\n\n  onClick(e) {\n    this.setState({\n      count: this.state.count + 1\n    });\n  }\n\n  render() {\n    return _react2.default.createElement(\n      \"div\",\n      null,\n      _react2.default.createElement(\n        \"h1\",\n        null,\n        this.state.count\n      ),\n      _react2.default.createElement(\n        \"button\",\n        { onClick: this.onClick },\n        \"Count Up!!\"\n      )\n    );\n  }\n}\n\nexports.default = App;"},"hash":"8b8e49858eaa370e2a8dcda1d77bd6af"}